setup.py
underline/__init__.py
underline/turntable.py
underline.turntable.egg-info/PKG-INFO
underline.turntable.egg-info/SOURCES.txt
underline.turntable.egg-info/dependency_links.txt
underline.turntable.egg-info/not-zip-safe
underline.turntable.egg-info/requires.txt
underline.turntable.egg-info/top_level.txt