Metadata-Version: 1.1
Name: underline.turntable
Version: 0.3
Summary: Speed and direction control of turntable.
Home-page: http://yeisoncardona.com
Author: Yeison Cardona
Author-email: yeisoneng@gmail.com
License: GPLv3
Keywords: Raspberry Pi 3,Stepper motor
Platform: UNKNOWN
Classifier: Development Status :: 1 - Planning
Classifier: Environment :: X11 Applications
Classifier: Intended Audience :: Science/Research
Classifier: License :: OSI Approved :: GNU Lesser General Public License v3 or later (LGPLv3+)
Classifier: Programming Language :: Python :: 3 :: Only
Classifier: Topic :: Scientific/Engineering
Classifier: Topic :: Software Development :: Libraries :: Python Modules
Classifier: Topic :: System :: Hardware
